setup.py
TicketTree.egg-info/PKG-INFO
TicketTree.egg-info/SOURCES.txt
TicketTree.egg-info/dependency_links.txt
TicketTree.egg-info/entry_points.txt
TicketTree.egg-info/top_level.txt
tickettree/__init__.py
tickettree/macros.py
tickettree/model.py
tickettree/web_ui.py