Metadata-Version: 1.0
Name: TicketTree
Version: 0.9
Summary: Ticket Tree
Home-page: http://trac-hacks.org/wiki/TicketTree
Author: Roberto Longobardi, Marco Cipriani
Author-email: seccanj@gmail.com
License: BSD. See the file LICENSE.txt contained in the package.
Download-URL: https://sourceforge.net/projects/tickettree4trac/files/
Keywords: trac plugin ticket tree organization structure
Platform: UNKNOWN
